setup.cfg
setup.py
pushmsg/__init__.py
pushmsg/pushmsg.py
pushmsg.egg-info/PKG-INFO
pushmsg.egg-info/SOURCES.txt
pushmsg.egg-info/dependency_links.txt
pushmsg.egg-info/requires.txt
pushmsg.egg-info/top_level.txt
scripts/pushmsg