Metadata-Version: 1.0
Name: pushmsg
Version: 0.2.2
Summary: IPython magic function to send notifications with Pushbullet
Home-page: https://github.com/nick-youngblut/pushmsg
Author: Nicholas Youngblut
Author-email: nyoungb2@gmail.com
License: MIT
Platform: UNKNOWN
